cli_template/__init__.py
cli_template/main.py
cli_template-0.4.2.dist-info/entry_points.txt
cli_template-0.4.2.dist-info/LICENSE
cli_template-0.4.2.dist-info/WHEEL
cli_template-0.4.2.dist-info/METADATA
cli_template-0.4.2.dist-info/RECORD
